ebo_test/__init__.py
ebo_test/cli.py
ebo_test-0.1.6.dist-info/METADATA
ebo_test-0.1.6.dist-info/WHEEL
ebo_test-0.1.6.dist-info/entry_points.txt
ebo_test-0.1.6.dist-info/RECORD
