Metadata-Version: 2.1
Name: ebo-test
Version: 0.1.6
Summary: 
Author: Emile Bosch
Author-email: emile@54hrs.com
Requires-Python: >=3.10,<4.0
Classifier: Programming Language :: Python :: 3
Classifier: Programming Language :: Python :: 3.10
Classifier: Programming Language :: Python :: 3.11
Classifier: Programming Language :: Python :: 3.12
Classifier: Programming Language :: Python :: 3.13
Requires-Dist: click (>=8.1.7,<9.0.0)
Requires-Dist: pluggy (>=1.5.0,<2.0.0)
Requires-Dist: requests (>=2.32.3,<3.0.0)
